DGLD/__init__.py
DGLD/models/__init__.py
DGLD/models/AAGNN/AAGNN_batch.py
DGLD/models/AAGNN/AAGNN_utils.py
DGLD/models/AAGNN/__init__.py
DGLD/models/ALARM/__init__.py
DGLD/models/ALARM/alarm_utils.py
DGLD/models/ALARM/models.py
DGLD/models/ANEMONE/__init__.py
DGLD/models/ANEMONE/anemone_utils.py
DGLD/models/ANEMONE/dataset.py
DGLD/models/ANEMONE/models.py
DGLD/models/AdONE/__init__.py
DGLD/models/AdONE/adone_utils.py
DGLD/models/AdONE/models.py
DGLD/models/AnomalyDAE/__init__.py
DGLD/models/AnomalyDAE/anomalydae_utils.py
DGLD/models/AnomalyDAE/models.py
DGLD/models/CONAD/__init__.py
DGLD/models/CONAD/conad_utils.py
DGLD/models/CONAD/models.py
DGLD/models/CoLA/__init__.py
DGLD/models/CoLA/colautils.py
DGLD/models/CoLA/dataset.py
DGLD/models/CoLA/model.py
DGLD/models/ComGA/__init__.py
DGLD/models/ComGA/comga_utils.py
DGLD/models/ComGA/models.py
DGLD/models/DOMINANT/__init__.py
DGLD/models/DOMINANT/dominant_utils.py
DGLD/models/DOMINANT/models.py
DGLD/models/DONE/__init__.py
DGLD/models/DONE/done_utils.py
DGLD/models/DONE/models.py
DGLD/models/GAAN/__init__.py
DGLD/models/GAAN/gaan_utils.py
DGLD/models/GAAN/model.py
DGLD/models/GCNAE/__init__.py
DGLD/models/GCNAE/gcnae_utils.py
DGLD/models/GCNAE/model.py
DGLD/models/GUIDE/__init__.py
DGLD/models/GUIDE/guide_utils.py
DGLD/models/GUIDE/model.py
DGLD/models/MLPAE/__init__.py
DGLD/models/MLPAE/mlpae_utils.py
DGLD/models/MLPAE/model.py
DGLD/models/ONE/__init__.py
DGLD/models/ONE/model.py
DGLD/models/ONE/one_utils.py
DGLD/models/SCAN/__init__.py
DGLD/models/SCAN/model.py
DGLD/models/SCAN/scan_utils.py
DGLD/models/SLGAD/SL_GAD_utils.py
DGLD/models/SLGAD/__init__.py
DGLD/models/SLGAD/dataset.py
DGLD/models/SLGAD/model.py
DGLD/modules/__init__.py
DGLD/modules/dglAug/__init__.py
DGLD/modules/dglAug/augs.py
DGLD/modules/dglAug/transforms/__init__.py
DGLD/modules/dglAug/transforms/feature_dropout.py
DGLD/modules/dglAug/transforms/node_shuffle.py
DGLD/modules/dglAug/transforms/random_mask.py
DGLD/utils/__init__.py
DGLD-0.3.0.dist-info/METADATA
DGLD-0.3.0.dist-info/WHEEL
DGLD-0.3.0.dist-info/top_level.txt
DGLD-0.3.0.dist-info/RECORD
